{"RMWi9D7VlxxmGIDMgB5D7Q==":"c01-400x326.png","Kqyh64uP/pLYNRA+vWvNEg==":"f01-400x327.png","B0274qX1/8j1iGZbthppeA==":"b01-400x326.png","9q55dr1Q0X+Weaw8KekOcA==":"004-626x468.jpg","fHG1sc6mYTvmG80hahzPnw==":"003-631x394.jpg","zYOMie2JMRVlUL0hbar2qQ==":"index-3-400x150.jpg","+7+booSDwJNRPsk33hEFAw==":"002-1582x1179.jpg","opQDgR6cLyDhZveHbdwP+w==":"002-1933x1440.jpg","yxmjcwHauVtiJy5oxVkF9A==":"upccbanner.gif","1+iOkwrsoMGq+IBNo4FmYg==":"002-510x380.jpg","v0jjafm6jYuxzSH9zFExQw==":"001-510x315.jpg","Jg0asc/EBJh/3UiqFKSphg==":"004-510x381.jpg","hCyfTg4m9DA7Dp1jQ8Wscw==":"003-510x318.jpg"}